{
  "collectionName": "components_sections_section_collections",
  "info": {
    "displayName": "section_collections",
    "icon": "infinity"
  },
  "options": {},
  "attributes": {
    "collection_hero_img": {
      "allowedTypes": [
        "images"
      ],
      "type": "media",
      "multiple": false
    },
    "collection_image_portrait": {
      "allowedTypes": [
        "images"
      ],
      "type": "media",
      "multiple": false
    },
    "collection_full_width_video": {
      "allowedTypes": [
        "images",
        "videos"
      ],
      "type": "media",
      "multiple": false
    }
  }
}
